jsonschema_pydantic/VERSION
jsonschema_pydantic/__init__.py
jsonschema_pydantic/transform.py
jsonschema_pydantic-0.6.dist-info/LICENSE
jsonschema_pydantic-0.6.dist-info/METADATA
jsonschema_pydantic-0.6.dist-info/WHEEL
jsonschema_pydantic-0.6.dist-info/top_level.txt
jsonschema_pydantic-0.6.dist-info/RECORD
